djangorestframework_sav-0.1.0.dist-info/DESCRIPTION.rst
djangorestframework_sav-0.1.0.dist-info/METADATA
djangorestframework_sav-0.1.0.dist-info/metadata.json
djangorestframework_sav-0.1.0.dist-info/RECORD
djangorestframework_sav-0.1.0.dist-info/top_level.txt
djangorestframework_sav-0.1.0.dist-info/WHEEL
rest_framework_sav/__init__.py
rest_framework_sav/views.py
